{
  "blocklist": {
    "name": "block.57d9fd65ad.p4f436.txt",
    "updated": "2026-03-08T08:42:10Z",
    "updated_format": "March 08, 2026 08:42:10 UTC",
    "lines": 760079,
    "lines_format": "760,079",
    "size": 15365269,
    "size_format": "14.7 MB"
  },
  "allowlist": {
    "name": "allow.3a3616dde3.vnbo7t.txt",
    "updated": "2026-03-08T08:42:01Z",
    "updated_format": "March 08, 2026 08:42:01 UTC",
    "lines": 15021,
    "lines_format": "15,021",
    "size": 197670,
    "size_format": "193.0 KB"
  }
}
